SmoothCache/__init__.py
SmoothCache/diffuser_cache_helper.py
SmoothCache/dit_cache_helper.py
SmoothCache/smooth_cache_helper.py
dit_smoothcache-0.1.1.dist-info/LICENSE
dit_smoothcache-0.1.1.dist-info/METADATA
dit_smoothcache-0.1.1.dist-info/WHEEL
dit_smoothcache-0.1.1.dist-info/top_level.txt
dit_smoothcache-0.1.1.dist-info/RECORD
