Metadata-Version: 2.1
Name: dit-smoothcache
Version: 0.1.1
Summary: Training-free acceleration toolkit for Diffusion Transformer pipelines
Home-page: https://github.com/Roblox/SmoothCache
Author: Roblox Core AI
License: UNKNOWN
Platform: UNKNOWN
License-File: LICENSE
Requires-Dist: torch (>=2.0.0)
